crawlabpy/__init__.py
crawlabpy/datapool.py
crawlabpy/encoder.py
crawlabpy/utils.py
crawlabpy-0.0.6.dist-info/LICENSE
crawlabpy-0.0.6.dist-info/METADATA
crawlabpy-0.0.6.dist-info/WHEEL
crawlabpy-0.0.6.dist-info/top_level.txt
crawlabpy-0.0.6.dist-info/RECORD
