Metadata-Version: 2.1
Name: crawlabpy
Version: 0.0.6
Summary: Crawlab implements with file uploader.
Home-page: https://github.com/gditsec/crawlabpy
Author: gditsec
Author-email: zhuangshq@gditsec.org.cn
License: UNKNOWN
Project-URL: Bug Tracker, https://github.com/gditsec/crawlabpy/issues
Platform: UNKNOWN
Classifier: Programming Language :: Python :: 3
Classifier: License :: OSI Approved :: MIT License
Classifier: Operating System :: OS Independent
Requires-Python: >=3.6
License-File: LICENSE
